{
  "id": "dyslexia_load_triggers_v1",
  "type": "questionnaire",
  "title": "Dyslexie Belastungsauslöser",
  "description": "Erfassung von Bedingungen, die Leseleistung beeinflussen.",
  "instructions": "Wähle die häufigsten Auslöser aus den letzten 2 Wochen.",
  "questions": [
    {
      "id": "dysl_t_1",
      "text": "Welche Faktoren erschweren dir das Lesen besonders?",
      "options": [
        "Zeitdruck",
        "Hintergrundgeräusche",
        "kleine Schrift",
        "Fremdwörter",
        "Müdigkeit"
      ]
    },
    {
      "id": "dysl_t_2",
      "text": "Welche Unterstützung hilft am meisten?",
      "options": [
        "größere Schrift",
        "Vorlesefunktion",
        "Pausen",
        "Markierhilfen",
        "Mitlesen zu zweit"
      ]
    }
  ]
}
